profiling_decorator/__init__.py
profiling_decorator/version.py
profiling_decorator-0.0.6.dist-info/METADATA
profiling_decorator-0.0.6.dist-info/WHEEL
profiling_decorator-0.0.6.dist-info/licenses/LICENSE
profiling_decorator-0.0.6.dist-info/RECORD
