Metadata-Version: 2.3
Name: profiling_decorator
Version: 0.0.6
Summary: Simplifies Python code profiling by offering an easy-to-use decorator for measuring function performance. Customize profiling with options for sort criteria and output format. Perfect for quickly identifying bottlenecks.
Project-URL: Homepage, https://github.com/CTPassion/profiling-decorator
Project-URL: Issues, https://github.com/CTPassion/profiling-decorator/issues
Author-email: Joshua Brumpton <ja.brumpton@gmail.com>
License-File: LICENSE
Classifier: License :: OSI Approved :: Apache Software License
Classifier: Operating System :: OS Independent
Classifier: Programming Language :: Python :: 3
Requires-Python: >=3.8
Provides-Extra: dev
Requires-Dist: black; extra == 'dev'
Provides-Extra: test
Requires-Dist: pytest; extra == 'test'
Requires-Dist: pytest-asyncio; extra == 'test'
